{
  "spent": [
    {
      "id": "38a0",
      "description": "ifood",
      "value": 50,
      "date": "04/02/25",
      "category": "alimentacao"
    },
    {
      "id": "1be7",
      "description": "Licenciamento",
      "value": 480,
      "date": "13/01/25",
      "category": "imposto"
    },
    {
      "id": "1747",
      "description": "FORD",
      "value": "50.480",
      "date": "2024-01-31",
      "category": "imprevisto"
    },
    {
      "id": "6efc",
      "description": "placa de video nova",
      "value": "4000",
      "date": "2025-02-09",
      "category": "outro"
    },
    {
      "id": "b1b3",
      "description": "fone de ouvido",
      "value": "390",
      "date": "2025-02-09",
      "category": "outro"
    },
    {
      "id": "cdd3",
      "description": "tv ",
      "value": "5000",
      "date": "2025-02-09",
      "category": "outro"
    }
  ]
}